{"Lista de estados":[{"isAccept":false,"Nombre del estado":"q0"},{"isAccept":false,"Nombre del estado":"q1"},{"isAccept":false,"Nombre del estado":"q2"}],"Estado inicial":{"isAccept":false,"Nombre del estado":"q0"},"Lista de estados aceptables":[{"isAccept":false,"Nombre del estado":"q1"}],"Lista de transiciones":[{"From":{"isAccept":false,"Name":"q0"},"To":{"isAccept":false,"Name":"q1"},"Character":"a"},{"From":{"isAccept":false,"Name":"q1"},"To":{"isAccept":false,"Name":"q0"},"Character":"b"},{"From":{"isAccept":false,"Name":"q1"},"To":{"isAccept":false,"Name":"q0"},"Character":"a"},{"From":{"isAccept":false,"Name":"q1"},"To":{"isAccept":false,"Name":"q2"},"Character":"b"},{"From":{"isAccept":false,"Name":"q2"},"To":{"isAccept":false,"Name":"q2"},"Character":"a"},{"From":{"isAccept":false,"Name":"q2"},"To":{"isAccept":false,"Name":"q1"},"Character":"b"}],"Alfabeto":[{"1":"a"},{"2":"b"}]}